{
    "totalObjectCount": 59473,
    "totalObjectSize": 3936497604608,
    "totalObjectDownload": 94618,
    "byUsers": [
        {
            "sub": "126",
            "count": 59,
            "totalSize": 11557857280,
            "totalDownload": 0
        },
        {
            "sub": "1370",
            "count": 78,
            "totalSize": 0,
            "totalDownload": 1
        },
        {
            "sub": "634",
            "count": 81,
            "totalSize": 511672320,
            "totalDownload": 0
        },
        {
            "sub": "1682",
            "count": 20,
            "totalSize": 1419653120,
            "totalDownload": 21
        },
        {
            "sub": "1092",
            "count": 70,
            "totalSize": 2031411200,
            "totalDownload": 0
        },
        {
            "sub": "1722",
            "count": 384,
            "totalSize": 0,
            "totalDownload": 3
        },
        {
            "sub": "1653",
            "count": 119,
            "totalSize": 0,
            "totalDownload": 1
        },
        {
            "sub": "148",
            "count": 423,
            "totalSize": 1513338880,
            "totalDownload": 274
        },
        {
            "sub": "1594",
            "count": 640,
            "totalSize": 32254638080,
            "totalDownload": 118
        },
        {
            "sub": "1376",
            "count": 394,
            "totalSize": 7250022400,
            "totalDownload": 23
        },
        {
            "sub": "1710",
            "count": 35,
            "totalSize": 0,
            "totalDownload": 7
        },
        {
            "sub": "1717",
            "count": 78,
            "totalSize": 0,
            "totalDownload": 1
        },
        {
            "sub": "822",
            "count": 43,
            "totalSize": 2030828083200,
            "totalDownload": 221
        },
        {
            "sub": "1348",
            "count": 15,
            "totalSize": 0,
            "totalDownload": 22
        },
        {
            "sub": "785",
            "count": 210,
            "totalSize": 2372689920,
            "totalDownload": 0
        },
        {
            "sub": "117",
            "count": 1,
            "totalSize": 415232000,
            "totalDownload": 0
        },
        {
            "sub": "993",
            "count": 2,
            "totalSize": 482734080,
            "totalDownload": 0
        },
        {
            "sub": "1721",
            "count": 1360,
            "totalSize": 0,
            "totalDownload": 0
        },
        {
            "sub": "1351",
            "count": 118,
            "totalSize": 48660480,
            "totalDownload": 354
        },
        {
            "sub": "1696",
            "count": 215,
            "totalSize": 0,
            "totalDownload": 3
        },
        {
            "sub": "1460",
            "count": 5,
            "totalSize": 727265280,
            "totalDownload": 1
        },
        {
            "sub": "704",
            "count": 258,
            "totalSize": 3124439040,
            "totalDownload": 18
        },
        {
            "sub": "1183",
            "count": 386,
            "totalSize": 6173153280,
            "totalDownload": 29
        },
        {
            "sub": "123",
            "count": 129,
            "totalSize": 279900160,
            "totalDownload": 9
        },
        {
            "sub": "56",
            "count": 747,
            "totalSize": 34368696320,
            "totalDownload": 3
        },
        {
            "sub": "1711",
            "count": 39,
            "totalSize": 0,
            "totalDownload": 1
        },
        {
            "sub": "1714",
            "count": 2,
            "totalSize": 59555840,
            "totalDownload": 4
        },
        {
            "sub": "1383",
            "count": 208,
            "totalSize": 4191692800,
            "totalDownload": 2
        },
        {
            "sub": "1503",
            "count": 787,
            "totalSize": 33246822400,
            "totalDownload": 237
        },
        {
            "sub": "1709",
            "count": 144,
            "totalSize": 0,
            "totalDownload": 0
        },
        {
            "sub": "110",
            "count": 4,
            "totalSize": 16916480,
            "totalDownload": 4
        },
        {
            "sub": "1705",
            "count": 16,
            "totalSize": 0,
            "totalDownload": 0
        },
        {
            "sub": "1716",
            "count": 54,
            "totalSize": 0,
            "totalDownload": 0
        },
        {
            "sub": "1703",
            "count": 137,
            "totalSize": 1313208320,
            "totalDownload": 2
        },
        {
            "sub": "1665",
            "count": 591,
            "totalSize": 0,
            "totalDownload": 0
        },
        {
            "sub": "1317",
            "count": 334,
            "totalSize": 3639480320,
            "totalDownload": 1
        },
        {
            "sub": "1699",
            "count": 119,
            "totalSize": 0,
            "totalDownload": 1
        },
        {
            "sub": "1697",
            "count": 2927,
            "totalSize": 0,
            "totalDownload": 2
        },
        {
            "sub": "1720",
            "count": 468,
            "totalSize": 0,
            "totalDownload": 0
        },
        {
            "sub": "1649",
            "count": 1111,
            "totalSize": 42761625600,
            "totalDownload": 387
        },
        {
            "sub": "1713",
            "count": 2,
            "totalSize": 7004160,
            "totalDownload": 8
        },
        {
            "sub": "1379",
            "count": 240,
            "totalSize": 3237437440,
            "totalDownload": 42
        },
        {
            "sub": "1581",
            "count": 125,
            "totalSize": 67717457920,
            "totalDownload": 0
        },
        {
            "sub": "1712",
            "count": 1319,
            "totalSize": 0,
            "totalDownload": 2
        },
        {
            "sub": "1724",
            "count": 2128,
            "totalSize": 0,
            "totalDownload": 1
        },
        {
            "sub": "170",
            "count": 1,
            "totalSize": 8294400,
            "totalDownload": 6
        },
        {
            "sub": "1172",
            "count": 1071,
            "totalSize": 18766131200,
            "totalDownload": 0
        },
        {
            "sub": "146",
            "count": 1,
            "totalSize": 20480,
            "totalDownload": 7
        },
        {
            "sub": "974",
            "count": 126,
            "totalSize": 25834987520,
            "totalDownload": 0
        },
        {
            "sub": "1384",
            "count": 1,
            "totalSize": 381798400,
            "totalDownload": 0
        },
        {
            "sub": "1604",
            "count": 1534,
            "totalSize": 4756029440,
            "totalDownload": 0
        },
        {
            "sub": "1704",
            "count": 595,
            "totalSize": 0,
            "totalDownload": 271
        },
        {
            "sub": "1692",
            "count": 3,
            "totalSize": 28395520,
            "totalDownload": 3
        },
        {
            "sub": "1169",
            "count": 25,
            "totalSize": 1131253760,
            "totalDownload": 0
        },
        {
            "sub": "1210",
            "count": 19,
            "totalSize": 470374400,
            "totalDownload": 0
        },
        {
            "sub": "135",
            "count": 2,
            "totalSize": 27187200,
            "totalDownload": 6
        },
        {
            "sub": "1702",
            "count": 132,
            "totalSize": 0,
            "totalDownload": 0
        },
        {
            "sub": "1167",
            "count": 575,
            "totalSize": 20308029440,
            "totalDownload": 654
        },
        {
            "sub": "16",
            "count": 13606,
            "totalSize": 444888207360,
            "totalDownload": 1766
        },
        {
            "sub": "506",
            "count": 9,
            "totalSize": 18063360,
            "totalDownload": 0
        },
        {
            "sub": "1",
            "count": 8,
            "totalSize": 1380290560,
            "totalDownload": 10
        },
        {
            "sub": "1708",
            "count": 468,
            "totalSize": 0,
            "totalDownload": 1
        },
        {
            "sub": "1175",
            "count": 738,
            "totalSize": 13023948800,
            "totalDownload": 23
        },
        {
            "sub": "174",
            "count": 16819,
            "totalSize": 515688908800,
            "totalDownload": 87434
        },
        {
            "sub": "1305",
            "count": 281,
            "totalSize": 23603200000,
            "totalDownload": 320
        },
        {
            "sub": "896",
            "count": 1,
            "totalSize": 258304000,
            "totalDownload": 3
        },
        {
            "sub": "947",
            "count": 3415,
            "totalSize": 200016062464,
            "totalDownload": 37
        },
        {
            "sub": "1209",
            "count": 999,
            "totalSize": 12856965120,
            "totalDownload": 228
        },
        {
            "sub": "1679",
            "count": 3,
            "totalSize": 2856960,
            "totalDownload": 0
        },
        {
            "sub": "73",
            "count": 5,
            "totalSize": 403118080,
            "totalDownload": 2
        },
        {
            "sub": "1226",
            "count": 208,
            "totalSize": 0,
            "totalDownload": 2
        },
        {
            "sub": "1623",
            "count": 2203,
            "totalSize": 361094529024,
            "totalDownload": 2042
        }
    ],
    "byDatatypes": [
        {
            "datatypeId": "5cb7711c44947d8aea8cb4f4",
            "datatypeName": "generic/image/svg",
            "count": 343,
            "totalSize": 299048960,
            "totalDownload": 0
        },
        {
            "datatypeId": "5f6aa135cfa3656ab4c9e245",
            "datatypeName": "neuro/dsistudio/tractmeasures",
            "count": 4,
            "totalSize": 317440,
            "totalDownload": 0
        },
        {
            "datatypeId": "5c390505f9109beac42b00df",
            "datatypeName": "neuro/fmap",
            "count": 52,
            "totalSize": 0,
            "totalDownload": 0
        },
        {
            "datatypeId": "592dded1436ee50ffd88f5d0",
            "datatypeName": "neuro/tractmasks",
            "count": 14,
            "totalSize": 7536640,
            "totalDownload": 6
        },
        {
            "datatypeId": "5e56dc330f7fa604cc3cc291",
            "datatypeName": "report/html",
            "count": 2326,
            "totalSize": 40968704000,
            "totalDownload": 1
        },
        {
            "datatypeId": "60ca4f058b8b7238324295d3",
            "datatypeName": "neuro/snr-stats",
            "count": 1808,
            "totalSize": 28549120,
            "totalDownload": 1
        },
        {
            "datatypeId": "5967b799b09297d8d831709e",
            "datatypeName": "generic/images",
            "count": 1,
            "totalSize": 15237120,
            "totalDownload": 0
        },
        {
            "datatypeId": "5bbfb28071454db2a890fbce",
            "datatypeName": "neuro/transform",
            "count": 148,
            "totalSize": 9640724480,
            "totalDownload": 125
        },
        {
            "datatypeId": "60f69321b991113f21b4fdf6",
            "datatypeName": "neuro/reho",
            "count": 1,
            "totalSize": 20480,
            "totalDownload": 7
        },
        {
            "datatypeId": "59b685a08e5d38b0b331ddc5",
            "datatypeName": "neuro/func/task",
            "count": 12420,
            "totalSize": 278178560000,
            "totalDownload": 682
        },
        {
            "datatypeId": "5c1a7489f9109beac4a88a1f",
            "datatypeName": "neuro/parcellation/volume",
            "count": 2681,
            "totalSize": 1023211520,
            "totalDownload": 492
        },
        {
            "datatypeId": "60007410aacf9e4edda691d4",
            "datatypeName": "neuro/eeg/eeglab",
            "count": 54,
            "totalSize": 0,
            "totalDownload": 0
        },
        {
            "datatypeId": "5c58aa5ef9109beac4b52f61",
            "datatypeName": "neuro/cortexmap",
            "count": 330,
            "totalSize": 9834721280,
            "totalDownload": 80
        },
        {
            "datatypeId": "599f305ad1f46fec1759f363",
            "datatypeName": "neuro/tractmeasures",
            "count": 2152,
            "totalSize": 9456220160,
            "totalDownload": 2
        },
        {
            "datatypeId": "5c536bf0f9109beac46adb45",
            "datatypeName": "neuro/csd",
            "count": 22,
            "totalSize": 861081600,
            "totalDownload": 22
        },
        {
            "datatypeId": "5ed0352de3f453b13b267dae",
            "datatypeName": "generic/network",
            "count": 1973,
            "totalSize": 123668480,
            "totalDownload": 718
        },
        {
            "datatypeId": "5cc1d64c44947d8aea6b2d8b",
            "datatypeName": "neuro/wmc",
            "count": 9,
            "totalSize": 1475860480,
            "totalDownload": 5
        },
        {
            "datatypeId": "5f6a9c7ecfa365847cc9dc75",
            "datatypeName": "neuro/dsistudio/tinytrack-s",
            "count": 4,
            "totalSize": 55889920,
            "totalDownload": 0
        },
        {
            "datatypeId": "5a281aee2c214c9ba83ce620",
            "datatypeName": "neuro/mask",
            "count": 7496,
            "totalSize": 722677760,
            "totalDownload": 559
        },
        {
            "datatypeId": "604a4553ebfe4559de3af944",
            "datatypeName": "generic/timeseries",
            "count": 613,
            "totalSize": 195338240,
            "totalDownload": 17
        },
        {
            "datatypeId": "59c3eae633fc1cf9ead71679",
            "datatypeName": "raw",
            "count": 690,
            "totalSize": 2100815462400,
            "totalDownload": 337
        },
        {
            "datatypeId": "5edd3b77c5972b8c47b3a2c3",
            "datatypeName": "neuro/parc-stats",
            "count": 10872,
            "totalSize": 571054080,
            "totalDownload": 46245
        },
        {
            "datatypeId": "58c33bcee13a50849b25879a",
            "datatypeName": "neuro/anat/t1w",
            "count": 5853,
            "totalSize": 70086584320,
            "totalDownload": 2409
        },
        {
            "datatypeId": "5c478b7bf9109beac4520be6",
            "datatypeName": "neuro/parcellation/surface-deprecated",
            "count": 1913,
            "totalSize": 52111933440,
            "totalDownload": 1863
        },
        {
            "datatypeId": "5a79df48d071a1753f1d661b",
            "datatypeName": "neuro/tensor",
            "count": 78,
            "totalSize": 843591680,
            "totalDownload": 48
        },
        {
            "datatypeId": "5907d922436ee50ffde9c549",
            "datatypeName": "neuro/track/tck",
            "count": 14,
            "totalSize": 8336056320,
            "totalDownload": 3
        },
        {
            "datatypeId": "600074f6aacf9e7acda691d7",
            "datatypeName": "neuro/eeg/edf",
            "count": 195,
            "totalSize": 0,
            "totalDownload": 1
        },
        {
            "datatypeId": "58cb22c8e13a50849b25882e",
            "datatypeName": "neuro/freesurfer",
            "count": 3082,
            "totalSize": 931688669184,
            "totalDownload": 39992
        },
        {
            "datatypeId": "6000714baacf9e22a6a691c8",
            "datatypeName": "neuro/meg/ctf",
            "count": 10,
            "totalSize": 0,
            "totalDownload": 15
        },
        {
            "datatypeId": "58c33c5fe13a50849b25879b",
            "datatypeName": "neuro/dwi",
            "count": 1221,
            "totalSize": 372629643264,
            "totalDownload": 594
        },
        {
            "datatypeId": "5be9ea0315a8683a39a1ebd9",
            "datatypeName": "neuro/rois",
            "count": 602,
            "totalSize": 34587801600,
            "totalDownload": 150
        },
        {
            "datatypeId": "58cb234be13a50849b25882f",
            "datatypeName": "neuro/dtiinit",
            "count": 56,
            "totalSize": 7849758720,
            "totalDownload": 0
        },
        {
            "datatypeId": "5b956f6cd7b3f1e24e9121ce",
            "datatypeName": "neuro/track/trk",
            "count": 14,
            "totalSize": 1237411840,
            "totalDownload": 11
        },
        {
            "datatypeId": "5f6957e2cfa3659a64c96606",
            "datatypeName": "neuro/dsistudio/fib",
            "count": 4,
            "totalSize": 188743680,
            "totalDownload": 0
        },
        {
            "datatypeId": "5c4f6a8af9109beac4b3dae0",
            "datatypeName": "neuro/regressors",
            "count": 2318,
            "totalSize": 2598512640,
            "totalDownload": 232
        },
        {
            "datatypeId": "594c0325fa1d2e5a1f0beda5",
            "datatypeName": "neuro/anat/t2w",
            "count": 57,
            "totalSize": 28579840,
            "totalDownload": 1
        },
        {
            "datatypeId": "5d34d9f744947d8aea0e0d2f",
            "datatypeName": "neuro/conmat",
            "count": 43,
            "totalSize": 36433920,
            "totalDownload": 0
        }
    ],
    "byProjects": [
        {
            "projectId": "5d2fb9756c03750a8a525343",
            "projectName": "Inherited Retinal Disease",
            "count": 283,
            "totalSize": 9420503040,
            "totalDownload": 252
        },
        {
            "projectId": "5f64dfd2cfa3659c95c8ef6b",
            "projectName": "TBI PTSD IRAD",
            "count": 70,
            "totalSize": 2031411200,
            "totalDownload": 0
        },
        {
            "projectId": "60e1ad3f4cb704f328056db3",
            "projectName": "Soccer",
            "count": 300,
            "totalSize": 15465994240,
            "totalDownload": 151
        },
        {
            "projectId": "60f54fdbb991113d57b42714",
            "projectName": "Forrest Gump",
            "count": 1319,
            "totalSize": 0,
            "totalDownload": 2
        },
        {
            "projectId": "5e2b98fbe51f7a9aeb88c43c",
            "projectName": "NSD 3T - Diffusion",
            "count": 24,
            "totalSize": 15323852800,
            "totalDownload": 16
        },
        {
            "projectId": "60e5879f4cb70402ae06bb9c",
            "projectName": "new2",
            "count": 250,
            "totalSize": 9495838720,
            "totalDownload": 78
        },
        {
            "projectId": "5faaf395afcdcc9b5ec48094",
            "projectName": "UCLA SCHZ",
            "count": 234,
            "totalSize": 3041566720,
            "totalDownload": 138
        },
        {
            "projectId": "60e82234ddc2dfc5f563c5a2",
            "projectName": "resting state fmri - HOI toolbox",
            "count": 2531,
            "totalSize": 0,
            "totalDownload": 1
        },
        {
            "projectId": "6021e00fab40cab2174c6861",
            "projectName": " HBN_CBIC_dwi_new",
            "count": 198,
            "totalSize": 53784821760,
            "totalDownload": 17791
        },
        {
            "projectId": "5f9b17f0e138ec7dd04db56e",
            "projectName": "HBN_RU",
            "count": 502,
            "totalSize": 407633920,
            "totalDownload": 29982
        },
        {
            "projectId": "60ff719eb991117793b94c07",
            "projectName": "Brain Correlates of Math Development",
            "count": 1360,
            "totalSize": 0,
            "totalDownload": 0
        },
        {
            "projectId": "60eea60dddc2df9f0d65da9b",
            "projectName": "Balloon Analog Risk-taking Task",
            "count": 16,
            "totalSize": 0,
            "totalDownload": 0
        },
        {
            "projectId": "5f9ad451e138ec0b5e4d96f4",
            "projectName": "HBN_CBIC",
            "count": 342,
            "totalSize": 46735360,
            "totalDownload": 344
        },
        {
            "projectId": "60f72f6db991115e07b53984",
            "projectName": "rsfMRI_single_session_EEG_NF",
            "count": 208,
            "totalSize": 0,
            "totalDownload": 2
        },
        {
            "projectId": "5f4d3d2a42c1728f7d6440b0",
            "projectName": "White Matter and Learning (WML)",
            "count": 3,
            "totalSize": 7321600,
            "totalDownload": 0
        },
        {
            "projectId": "60a3dff103bcad0e9c7d2ba2",
            "projectName": "Longitudinal clinical score prediction",
            "count": 1534,
            "totalSize": 4756029440,
            "totalDownload": 0
        },
        {
            "projectId": "60b733550ad40d4d00ca2560",
            "projectName": "A_P",
            "count": 28,
            "totalSize": 58661171200,
            "totalDownload": 0
        },
        {
            "projectId": "5fd26164ff0438c6d72882e6",
            "projectName": "ABCD BL Replication Paper",
            "count": 47,
            "totalSize": 1454080,
            "totalDownload": 0
        },
        {
            "projectId": "5f66983acfa365f34fc9287f",
            "projectName": "Flanker",
            "count": 738,
            "totalSize": 13023948800,
            "totalDownload": 23
        },
        {
            "projectId": "6073fb94e8c764833de3c717",
            "projectName": "STRK_NEW_1",
            "count": 45,
            "totalSize": 332144640,
            "totalDownload": 0
        },
        {
            "projectId": "610086d5b991119a21b9ecc7",
            "projectName": "Okra",
            "count": 1,
            "totalSize": 3502080,
            "totalDownload": 3
        },
        {
            "projectId": "60fd099bb991112a0db7f4bd",
            "projectName": "Flanker task (event-related)",
            "count": 78,
            "totalSize": 0,
            "totalDownload": 1
        },
        {
            "projectId": "60ca475c8b8b721961429422",
            "projectName": "CAM-CAN Aging Vertical Tracts",
            "count": 16,
            "totalSize": 282695680,
            "totalDownload": 9
        },
        {
            "projectId": "5f9c1b86e138ec57c14dd8b9",
            "projectName": "HBN_SI",
            "count": 249,
            "totalSize": 39946240,
            "totalDownload": 15818
        },
        {
            "projectId": "60ff1411b9911144e6b8de6a",
            "projectName": "task1-vsm",
            "count": 178,
            "totalSize": 7796551680,
            "totalDownload": 44
        },
        {
            "projectId": "60e15d9d4cb704002b053e84",
            "projectName": "fmri ts trial project - HOI toolbox",
            "count": 396,
            "totalSize": 0,
            "totalDownload": 1
        },
        {
            "projectId": "60fbff5eb99111fce0b79d0c",
            "projectName": "Drumming_DTI (S1)",
            "count": 220,
            "totalSize": 2277826560,
            "totalDownload": 204
        },
        {
            "projectId": "60e57d194cb70478d706b558",
            "projectName": "new1",
            "count": 454,
            "totalSize": 16937953280,
            "totalDownload": 150
        },
        {
            "projectId": "60ecfcd8ddc2df1088654a64",
            "projectName": "Emotion regulation in the Ageing Brain, University of Reading, BBSRC",
            "count": 67,
            "totalSize": 0,
            "totalDownload": 0
        },
        {
            "projectId": "60f65807b991114050b4f068",
            "projectName": "Functional Connectivity of Music-Induced Analgesia in Fibromyalgia",
            "count": 80,
            "totalSize": 0,
            "totalDownload": 79
        },
        {
            "projectId": "60fccdd7b99111531ab7e564",
            "projectName": "EEG: Visual Working Memory + Cabergoline Challenge",
            "count": 54,
            "totalSize": 0,
            "totalDownload": 0
        },
        {
            "projectId": "604a38f7ebfe452ca73af4e3",
            "projectName": "CRE_ConnectivityNetworks_LTU_Cumberland",
            "count": 1,
            "totalSize": 381798400,
            "totalDownload": 0
        },
        {
            "projectId": "60feefe8b9911122ceb8b012",
            "projectName": "Neural Processing of Emotional Musical and Nonmusical Stimuli in Depression",
            "count": 234,
            "totalSize": 0,
            "totalDownload": 0
        },
        {
            "projectId": "60ff1535b99111447bb8e17a",
            "projectName": " Drumming_DTI (S9) ",
            "count": 39,
            "totalSize": 489912320,
            "totalDownload": 48
        },
        {
            "projectId": "5a74b26ab7f7fb00495482bd",
            "projectName": "Hetrick_DTI",
            "count": 257,
            "totalSize": 537415680,
            "totalDownload": 0
        },
        {
            "projectId": "60be6f1f0ad40d3218cbac4a",
            "projectName": "UCLA_CNP",
            "count": 2,
            "totalSize": 102400,
            "totalDownload": 0
        },
        {
            "projectId": "60d918becdfdb57ca0009e97",
            "projectName": "ABIDE-I",
            "count": 1903,
            "totalSize": 345628534784,
            "totalDownload": 1891
        },
        {
            "projectId": "5e2da94ac9ea6d7835e6cc8c",
            "projectName": "Test FMRI",
            "count": 3,
            "totalSize": 336773120,
            "totalDownload": 2
        },
        {
            "projectId": "5fa9e18eafcdcc22a2c45378",
            "projectName": "UCLA Control",
            "count": 765,
            "totalSize": 9815398400,
            "totalDownload": 90
        },
        {
            "projectId": "5ed5e32ada664512808e8800",
            "projectName": "test - Neural Processing of Emotional Musical and Nonmusical Stimuli in Depression",
            "count": 210,
            "totalSize": 2372689920,
            "totalDownload": 0
        },
        {
            "projectId": "602aa19f3a001184324ba16e",
            "projectName": "HBN",
            "count": 3415,
            "totalSize": 200016062464,
            "totalDownload": 37
        },
        {
            "projectId": "60f1786cddc2df5de266d0c1",
            "projectName": "The generality of self-control",
            "count": 144,
            "totalSize": 0,
            "totalDownload": 0
        },
        {
            "projectId": "5f6cc0816bbee389b59a1819",
            "projectName": "Human Connectome Young Adult - Test-Retest Dataset",
            "count": 256,
            "totalSize": 288378839040,
            "totalDownload": 86
        },
        {
            "projectId": "5e835594dd840e5718e97b1e",
            "projectName": "ABCD fibers",
            "count": 9,
            "totalSize": 18063360,
            "totalDownload": 0
        },
        {
            "projectId": "5f1ef04cbeafe9241061ecb0",
            "projectName": "Freesurfer_NKI_Rockland_FULL_v7",
            "count": 2156,
            "totalSize": 110387200,
            "totalDownload": 0
        },
        {
            "projectId": "6054524d9feaaef54f9aee68",
            "projectName": "Myeline Final",
            "count": 1,
            "totalSize": 415232000,
            "totalDownload": 0
        },
        {
            "projectId": "60f2f8b29fb0ac1839818f47",
            "projectName": "Neural Processing of Emotional Musical and Nonmusical Stimuli in Depression",
            "count": 39,
            "totalSize": 0,
            "totalDownload": 1
        },
        {
            "projectId": "6114f966a5a04c0b4ff98f97",
            "projectName": "Drumming_DTI(S13)",
            "count": 13,
            "totalSize": 252784640,
            "totalDownload": 24
        },
        {
            "projectId": "5fd8a8ca57aacd56f32edf09",
            "projectName": "Noddi_Test",
            "count": 334,
            "totalSize": 3639480320,
            "totalDownload": 1
        },
        {
            "projectId": "5dd31542c4ae2815c12a0b2d",
            "projectName": "MCI Data FreeSurfer recon-all",
            "count": 81,
            "totalSize": 511672320,
            "totalDownload": 0
        },
        {
            "projectId": "59cbd18ff32356076a887fe4",
            "projectName": "IU Concussion Biobank",
            "count": 5,
            "totalSize": 1094553600,
            "totalDownload": 4
        },
        {
            "projectId": "5f6a4786cfa3651944c9c186",
            "projectName": "BUndle ANalytics (BUAN)",
            "count": 4,
            "totalSize": 16916480,
            "totalDownload": 4
        },
        {
            "projectId": "603132d53a00115f3a4f8e47",
            "projectName": "STRK_new",
            "count": 81,
            "totalSize": 599470080,
            "totalDownload": 0
        },
        {
            "projectId": "5fdd2da657aacd5e682f5145",
            "projectName": "ABCD_NSSI",
            "count": 5,
            "totalSize": 727265280,
            "totalDownload": 1
        },
        {
            "projectId": "60eaafd4ddc2df40a6649ab5",
            "projectName": "Examining effects of arousal on responses to salient and non-salient stimuli in younger and older adults",
            "count": 52,
            "totalSize": 0,
            "totalDownload": 2
        },
        {
            "projectId": "5dd6de36936ca362d3c55a04",
            "projectName": "Soichi's Personal",
            "count": 3,
            "totalSize": 1008066560,
            "totalDownload": 4
        },
        {
            "projectId": "60e7b646ddc2dfdccb63a898",
            "projectName": "gambling neuromatch",
            "count": 130,
            "totalSize": 0,
            "totalDownload": 0
        },
        {
            "projectId": "60a5102d22b42a67c46f7b72",
            "projectName": "Narratives",
            "count": 640,
            "totalSize": 32254638080,
            "totalDownload": 118
        },
        {
            "projectId": "60fa62c1b991119ddab697b6",
            "projectName": "p6055L",
            "count": 20,
            "totalSize": 1419653120,
            "totalDownload": 21
        },
        {
            "projectId": "60708cf9c7f80a684995e0b1",
            "projectName": "Pediatric Imaging, Neurocognition, and Genetics (PING) Dataset - SIEMENS only",
            "count": 681,
            "totalSize": 4246671360,
            "totalDownload": 114
        },
        {
            "projectId": "60ecf87bddc2dfdcab6546dc",
            "projectName": "Functional Connectivity of Music-Induced Analgesia in Fibromyalgia",
            "count": 80,
            "totalSize": 0,
            "totalDownload": 80
        },
        {
            "projectId": "60f535c1b991111079b418a6",
            "projectName": "COGENT",
            "count": 2,
            "totalSize": 27187200,
            "totalDownload": 6
        },
        {
            "projectId": "60c7ab687657d9caeae13522",
            "projectName": "Budapest_Hotel_movie",
            "count": 281,
            "totalSize": 23603200000,
            "totalDownload": 320
        },
        {
            "projectId": "6047ccf5ebfe4512043a9a65",
            "projectName": "CRE_ConnectivityNetworks_LTU_Davidson",
            "count": 208,
            "totalSize": 4191692800,
            "totalDownload": 2
        },
        {
            "projectId": "5f6d12426bbee324dc9a68f4",
            "projectName": "Daselaar Replication",
            "count": 1071,
            "totalSize": 18766131200,
            "totalDownload": 0
        },
        {
            "projectId": "606bde8bc7f80a4df794b2d4",
            "projectName": "HCP test-retest",
            "count": 43,
            "totalSize": 2030828083200,
            "totalDownload": 221
        },
        {
            "projectId": "60fe5fd0b99111c25db862a3",
            "projectName": "Drumming_DTI (S4)",
            "count": 79,
            "totalSize": 618700800,
            "totalDownload": 72
        },
        {
            "projectId": "60ff197ab99111b1cab8ebae",
            "projectName": "task2-flanker",
            "count": 211,
            "totalSize": 8752189440,
            "totalDownload": 63
        },
        {
            "projectId": "5be9b84cd7b88f0026873917",
            "projectName": "JAT_TEST",
            "count": 5,
            "totalSize": 403118080,
            "totalDownload": 2
        },
        {
            "projectId": "60d6e499cdfdb5e670007c4f",
            "projectName": "fMRI preprocessing",
            "count": 3,
            "totalSize": 2856960,
            "totalDownload": 0
        },
        {
            "projectId": "5ffaba27c7f5c6608b28a71f",
            "projectName": "ADHD-Sleep",
            "count": 118,
            "totalSize": 48660480,
            "totalDownload": 354
        },
        {
            "projectId": "5f7b651f268f766ba129e172",
            "projectName": "Flanker task (event-related)",
            "count": 386,
            "totalSize": 6173153280,
            "totalDownload": 29
        },
        {
            "projectId": "601379c3c0810357edba5e8d",
            "projectName": "HBN_CUNY_R8_R9",
            "count": 210,
            "totalSize": 25825495040,
            "totalDownload": 17995
        },
        {
            "projectId": "60fb01d5b99111a201b72168",
            "projectName": "Freesurfer_PITT_PYS_Kaward",
            "count": 399,
            "totalSize": 24290150400,
            "totalDownload": 111
        },
        {
            "projectId": "60ff1637b9911196d2b8e3f7",
            "projectName": "Drumming_DTI (S15) ",
            "count": 30,
            "totalSize": 388679680,
            "totalDownload": 26
        },
        {
            "projectId": "601a6d90321a4ad16d6e9ad2",
            "projectName": "UCLA Consortium for Neuropsychiatric Phenomics LA5c Study",
            "count": 12,
            "totalSize": 244951040,
            "totalDownload": 0
        },
        {
            "projectId": "5fb3e1687e8ecbb378ab0d5e",
            "projectName": "preprocessing_fmriprep",
            "count": 126,
            "totalSize": 25834987520,
            "totalDownload": 0
        },
        {
            "projectId": "60ec4bfeddc2df283c64ee88",
            "projectName": "Identification of an Amygdala-Thalamic Circuit That Acts as a Central Gain Mechanism in Taste Perception",
            "count": 84,
            "totalSize": 0,
            "totalDownload": 0
        },
        {
            "projectId": "5ed85ccbda6645e74f8ee452",
            "projectName": "DONE_Freesurfer_PITT_PYS",
            "count": 204,
            "totalSize": 8376320,
            "totalDownload": 0
        },
        {
            "projectId": "60137616c0810338a5ba5c27",
            "projectName": "HBN_RU_R7_R8",
            "count": 226,
            "totalSize": 56801341440,
            "totalDownload": 570
        },
        {
            "projectId": "60eda691ddc2df85f9657dfc",
            "projectName": "MEG-BIDS OMEGA RestingState_sample",
            "count": 15,
            "totalSize": 0,
            "totalDownload": 22
        },
        {
            "projectId": "5c50b6f12daf2e0032f880eb",
            "projectName": "HCP Derivatives 3T - multishell",
            "count": 15,
            "totalSize": 25118720,
            "totalDownload": 0
        },
        {
            "projectId": "60e836c4ddc2dfee5863df10",
            "projectName": "Flanker task (event-related)",
            "count": 78,
            "totalSize": 0,
            "totalDownload": 1
        },
        {
            "projectId": "5fd37e5cdecf133f0daca92a",
            "projectName": "PING",
            "count": 25,
            "totalSize": 40898560,
            "totalDownload": 0
        },
        {
            "projectId": "60e587cd4cb704f2bc06bc73",
            "projectName": "new3",
            "count": 197,
            "totalSize": 8588267520,
            "totalDownload": 83
        },
        {
            "projectId": "60e05a944cb704612b04d8d5",
            "projectName": "Real-time EEG feedback on alpha power lateralization leads to behavioral improvements in a covert attention task",
            "count": 165,
            "totalSize": 0,
            "totalDownload": 1
        },
        {
            "projectId": "60e455c44cb70432be065663",
            "projectName": "Classification learning",
            "count": 119,
            "totalSize": 0,
            "totalDownload": 1
        },
        {
            "projectId": "6047cd06ebfe45c5c93a9a67",
            "projectName": "CRE_ConnectivityNetwork_LTU_Aspinall ",
            "count": 394,
            "totalSize": 7250022400,
            "totalDownload": 23
        },
        {
            "projectId": "60e05e804cb704544d04dbed",
            "projectName": "Dataset of EEG recordings of pediatric patients with epilepsy based on the 10-20 system ",
            "count": 30,
            "totalSize": 0,
            "totalDownload": 0
        },
        {
            "projectId": "60b656dd0ad40d3c42c9dec4",
            "projectName": "A_t2",
            "count": 4,
            "totalSize": 1030215680,
            "totalDownload": 0
        },
        {
            "projectId": "5ffc884d2ba0fba7a7e89132",
            "projectName": "Human Connectome Young adult – Full Dataset",
            "count": 3663,
            "totalSize": 14498058240,
            "totalDownload": 9
        },
        {
            "projectId": "60b96dac0ad40d1258ca81eb",
            "projectName": "Networks: Depression vs healthy participants",
            "count": 258,
            "totalSize": 3124439040,
            "totalDownload": 18
        },
        {
            "projectId": "60fdc005b9911155edb82d92",
            "projectName": "VisibleBrain",
            "count": 2,
            "totalSize": 59555840,
            "totalDownload": 4
        },
        {
            "projectId": "5ac2a489e182730027c55588",
            "projectName": "Human Olfactory Atlases",
            "count": 2,
            "totalSize": 8314880,
            "totalDownload": 13
        },
        {
            "projectId": "60e19f2e4cb704ec8f055a8e",
            "projectName": "Natural-image reconstruction fmri",
            "count": 591,
            "totalSize": 0,
            "totalDownload": 0
        },
        {
            "projectId": "60ff0c2db9911106beb8d298",
            "projectName": "Drumming_DTI (S6)",
            "count": 1,
            "totalSize": 9758720,
            "totalDownload": 18
        },
        {
            "projectId": "6039a82d78e65d5da9d17a18",
            "projectName": "AOMIC-ID1000",
            "count": 204,
            "totalSize": 10444800,
            "totalDownload": 207
        },
        {
            "projectId": "60f18f67ddc2df5f1166e4d4",
            "projectName": "Test",
            "count": 35,
            "totalSize": 0,
            "totalDownload": 7
        },
        {
            "projectId": "5d64733db29ac960ca2e797f",
            "projectName": "App Test",
            "count": 5,
            "totalSize": 372224000,
            "totalDownload": 6
        },
        {
            "projectId": "60f64fb8b9911148edb4ed7f",
            "projectName": "Functional Connectivity of Music-Induced Analgesia in Fibromyalgia",
            "count": 80,
            "totalSize": 0,
            "totalDownload": 0
        },
        {
            "projectId": "5ef2999fc1a7123359d2dc94",
            "projectName": "Freesurfer_NIMH_IRP",
            "count": 2162,
            "totalSize": 9804441600,
            "totalDownload": 349
        },
        {
            "projectId": "60e1bde24cb704a2ca05833c",
            "projectName": "Mouse_rest_awake",
            "count": 20,
            "totalSize": 0,
            "totalDownload": 2
        },
        {
            "projectId": "5fb1ccf37e8ecb8242aaca75",
            "projectName": "Cambridge Centre for Ageing and Neuroscience - Full Dataset",
            "count": 8541,
            "totalSize": 107348992000,
            "totalDownload": 1144
        },
        {
            "projectId": "6040056778e65de291d753ba",
            "projectName": "WML-prelim",
            "count": 20,
            "totalSize": 10864527360,
            "totalDownload": 0
        },
        {
            "projectId": "6155bff6fc8eb9552ff3fa6c",
            "projectName": "HBN_test_subset",
            "count": 5,
            "totalSize": 256000,
            "totalDownload": 302
        },
        {
            "projectId": "5cb8973c71a8630036207a6a",
            "projectName": "Athlete Microstructure Data",
            "count": 58,
            "totalSize": 4397404160,
            "totalDownload": 73
        },
        {
            "projectId": "60a7d07422b42a006570670c",
            "projectName": "dti",
            "count": 92,
            "totalSize": 8024002560,
            "totalDownload": 0
        },
        {
            "projectId": "60fef0f9b99111a79bb8b2e2",
            "projectName": "Neural Processing of Emotional Musical and Nonmusical Stimuli in Depression",
            "count": 234,
            "totalSize": 0,
            "totalDownload": 0
        },
        {
            "projectId": "60ec429fddc2df1d8264ecd5",
            "projectName": "New Project",
            "count": 2,
            "totalSize": 482734080,
            "totalDownload": 0
        },
        {
            "projectId": "60c236d652690c242171a643",
            "projectName": "trk",
            "count": 1,
            "totalSize": 2068480,
            "totalDownload": 0
        },
        {
            "projectId": "6102a548b99111cfe6bae9e4",
            "projectName": "SUDMEX_CONN: The Mexican dataset of cocaine use disorder patients.",
            "count": 282,
            "totalSize": 0,
            "totalDownload": 272
        },
        {
            "projectId": "60ecfc6addc2dfb9e8654909",
            "projectName": "SCA2 Diffusion Tensor Imaging",
            "count": 100,
            "totalSize": 0,
            "totalDownload": 0
        },
        {
            "projectId": "60f17918ddc2dfc3c566d254",
            "projectName": "TEST",
            "count": 468,
            "totalSize": 0,
            "totalDownload": 1
        },
        {
            "projectId": "60f9d516b99111ff56b66da5",
            "projectName": "Drumming_anatomy (t1w)",
            "count": 218,
            "totalSize": 16099645440,
            "totalDownload": 288
        },
        {
            "projectId": "60e7ba73ddc2df708163abaf",
            "projectName": "fmriprep_tutorial",
            "count": 7,
            "totalSize": 1313208320,
            "totalDownload": 2
        },
        {
            "projectId": "60f7ab18b9911112edb54a3f",
            "projectName": "My Default Project",
            "count": 1,
            "totalSize": 3502080,
            "totalDownload": 5
        },
        {
            "projectId": "5ec9c6921f44642cb49ea128",
            "projectName": "DONE_Freesurfer_PING",
            "count": 838,
            "totalSize": 74209280,
            "totalDownload": 7
        },
        {
            "projectId": "5e9c9255f1745d584ef66add",
            "projectName": "Glaucoma white matter microstructure",
            "count": 114,
            "totalSize": 275957760,
            "totalDownload": 0
        },
        {
            "projectId": "6102e5bcb9911123e0bb3f69",
            "projectName": "Longitudinal Brain Correlates of Multisensory Lexical Processing in Children",
            "count": 2128,
            "totalSize": 0,
            "totalDownload": 1
        },
        {
            "projectId": "5fc1e9cf1828bc1f50517d85",
            "projectName": "The Reading Brain Project L1 Adults",
            "count": 1,
            "totalSize": 258304000,
            "totalDownload": 3
        },
        {
            "projectId": "60e380ef4cb704b5bd062d00",
            "projectName": "New Project",
            "count": 210,
            "totalSize": 7739566080,
            "totalDownload": 76
        },
        {
            "projectId": "60ff12bfb991110e92b8db04",
            "projectName": "Drumming_DTI (S8) ",
            "count": 9,
            "totalSize": 176435200,
            "totalDownload": 18
        },
        {
            "projectId": "60e98be7ddc2dfcf0f645bec",
            "projectName": "Test Project 1",
            "count": 119,
            "totalSize": 0,
            "totalDownload": 1
        },
        {
            "projectId": "60dbb150cdfdb53928014261",
            "projectName": "Bias_Field_Correction_ANTs",
            "count": 3,
            "totalSize": 28395520,
            "totalDownload": 3
        },
        {
            "projectId": "60ff2210b99111247ab8fa17",
            "projectName": "Task3-WOP",
            "count": 398,
            "totalSize": 16698081280,
            "totalDownload": 130
        },
        {
            "projectId": "61017999b9911155bbba495d",
            "projectName": "Pattern Separation beyond the Hippocampus: A High-Resolution Whole-Brain Investigation of Mnemonic Discrimination in Healthy Adults",
            "count": 384,
            "totalSize": 0,
            "totalDownload": 3
        },
        {
            "projectId": "6114fa36a5a04cc1a9f990e2",
            "projectName": "Drumming_DTI(S12) ",
            "count": 11,
            "totalSize": 227338240,
            "totalDownload": 12
        },
        {
            "projectId": "5fa7683ae138ec67474ee17b",
            "projectName": "Working Memory Related Brain Network Connectivity in Individuals with Schizophrenia and Their Siblings",
            "count": 19,
            "totalSize": 470374400,
            "totalDownload": 0
        },
        {
            "projectId": "60c23d1752690cd7c571ae1d",
            "projectName": "Brain Genomics Superstruct Project",
            "count": 8546,
            "totalSize": 342156021760,
            "totalDownload": 3565
        },
        {
            "projectId": "60e9662addc2df2301645022",
            "projectName": "Examining effects of arousal on responses to salient and non-salient stimuli in younger and older adults",
            "count": 52,
            "totalSize": 0,
            "totalDownload": 110
        },
        {
            "projectId": "6114f863a5a04c9febf98d9e",
            "projectName": "Drumming_DTI(S14)",
            "count": 11,
            "totalSize": 227747840,
            "totalDownload": 11
        },
        {
            "projectId": "60e7174d4cb7040c8a0780d5",
            "projectName": "Cost Analysis TBI",
            "count": 132,
            "totalSize": 0,
            "totalDownload": 0
        },
        {
            "projectId": "6047ccf3ebfe4586493a9a64",
            "projectName": "CRE_ConnectivityNetworks_LTU_Barnewold",
            "count": 240,
            "totalSize": 3237437440,
            "totalDownload": 42
        },
        {
            "projectId": "614115a4c46a3dd0db9a1383",
            "projectName": "Human Connectome Young Adults Test-Retest Data set - fMRI Gradients Experiments",
            "count": 2,
            "totalSize": 83435520,
            "totalDownload": 1
        },
        {
            "projectId": "5f0f143b880bc16398a7abd3",
            "projectName": "Freesurfer_NCANDA_v7",
            "count": 576,
            "totalSize": 2328545280,
            "totalDownload": 393
        },
        {
            "projectId": "5fb6c9127e8ecbb09bab753f",
            "projectName": "Psych 517 Checkerboard Task",
            "count": 25,
            "totalSize": 1131253760,
            "totalDownload": 0
        },
        {
            "projectId": "60a4135103bcad75737d43ff",
            "projectName": "WMA tract endpoint reanalysis",
            "count": 475,
            "totalSize": 33806161920,
            "totalDownload": 3
        }
    ]
}